Lab02/alu.v
// Standard timescale directive for simulation timing.
`timescale 1ns / 1ps
// -------------------------------------------------------------------------
// Functional Units
// Each operation is implemented as a separate module.
// Artificial delays are applied to simulate specific hardware latencies.
// -------------------------------------------------------------------------

module forward_unit(input [7:0] data2, output reg [7:0] out);
    // FORWARD unit sends DATA2 to output.
    // Required delay: #1 time unit.
    // Triggered asynchronously when data2 changes.
    always @(*) #1 out = data2;
endmodule

module add_unit(input [7:0] data1, input [7:0] data2, output reg [7:0] out);
    // ADD unit computes DATA1 + DATA2.
    // Required delay: #2 time units.
    always @(*) #2 out = data1 + data2;
endmodule

module and_unit(input [7:0] data1, input [7:0] data2, output reg [7:0] out);
    // AND unit performs bitwise AND on DATA1 and DATA2.
    // Required delay: #1 time unit.
    always @(*) #1 out = data1 & data2;
endmodule

module or_unit(input [7:0] data1, input [7:0] data2, output reg [7:0] out);
    // OR unit performs bitwise OR on DATA1 and DATA2.
    // Required delay: #1 time unit.
    always @(*) #1 out = data1 | data2;
endmodule

// -------------------------------------------------------------------------
// Top-Level ALU Module
// Integrates functional units and multiplexes the output.
// -------------------------------------------------------------------------

module alu (DATA1, DATA2, RESULT, SELECT);
    // Interfaces as defined in the specification.
    input [7:0] DATA1, DATA2;
    input [2:0] SELECT;
    output reg [7:0] RESULT;

    // Internal wires connecting functional unit outputs to the multiplexer.
    wire [7:0] fwd_out, add_out, and_out, or_out;

    // Instantiate functional units. All units compute in parallel.
    forward_unit f1(.data2(DATA2), .out(fwd_out));
    add_unit     a1(.data1(DATA1), .data2(DATA2), .out(add_out));
    and_unit     an1(.data1(DATA1), .data2(DATA2), .out(and_out));
    or_unit      o1(.data1(DATA1), .data2(DATA2), .out(or_out));

    // Multiplexer logic uses a case structure to select the output.
    always @(*) begin
        case(SELECT)
            3'b000: RESULT = fwd_out; // Supports loadi, mov
            3'b001: RESULT = add_out; // Supports add, sub
            3'b010: RESULT = and_out; // Supports and
            3'b011: RESULT = or_out;  // Supports or
            
            // Unused bit combinations of the SELECT port default to zero.
            // This prevents the synthesis of unintended latches.
            default: RESULT = 8'b00000000; 
        endcase
    end
endmodule

Lab02/tb_alu.v
`timescale 1ns / 1ps

module tb_alu;

    // Testbench registers to drive inputs into the ALU.
    reg [7:0] DATA1;
    reg [7:0] DATA2;
    reg [2:0] SELECT;

    // Wire to observe the output from the ALU.
    wire [7:0] RESULT;

    // Instantiate the Unit Under Test (UUT).
    alu uut (
        .DATA1(DATA1),
        .DATA2(DATA2),
        .RESULT(RESULT),
        .SELECT(SELECT)
    );

    initial begin
        // GTKWave configuration: Generates the VCD file for timing visualization.
        $dumpfile("alu_waveform.vcd"); 
        $dumpvars(0, tb_alu);          

        // Monitor prints variable states to the console dynamically upon change.
        $monitor("Time: %0t | SELECT: %b | DATA1: %d | DATA2: %d | RESULT: %d", 
                 $time, SELECT, DATA1, DATA2, RESULT);

        // System Initialization
        DATA1 = 8'd0;
        DATA2 = 8'd0;
        SELECT = 3'b000;
        #10; // 10 ns interval to allow propagation

        // ---------------------------------------------------------
        // State 000: FORWARD
        // Expectation: RESULT = 25 after 1 time unit delay.
        // ---------------------------------------------------------
        DATA1 = 8'd10; 
        DATA2 = 8'd25; 
        SELECT = 3'b000;
        #10; 

        // ---------------------------------------------------------
        // State 001: ADD
        // Expectation: RESULT = 35 after 2 time units delay.
        // ---------------------------------------------------------
        DATA1 = 8'd10; 
        DATA2 = 8'd25; 
        SELECT = 3'b001;
        #10;

        // ---------------------------------------------------------
        // State 010: AND
        // Expectation: RESULT = 160 (10100000 in binary) after 1 time unit delay.
        // ---------------------------------------------------------
        DATA1 = 8'b11110000; 
        DATA2 = 8'b10101010; 
        SELECT = 3'b010;
        #10;

        // ---------------------------------------------------------
        // State 011: OR
        // Expectation: RESULT = 255 (11111111 in binary) after 1 time unit delay.
        // ---------------------------------------------------------
        DATA1 = 8'b11110000; 
        DATA2 = 8'b00001111; 
        SELECT = 3'b011;
        #10;

        // ---------------------------------------------------------
        // States 1XX: Reserved
        // Expectation: RESULT = 0 immediately (handled by default case).
        // ---------------------------------------------------------
        DATA1 = 8'd100; 
        DATA2 = 8'd100; 
        SELECT = 3'b100; 
        #5;
        
        SELECT = 3'b111; 
        #10;

        // Terminate simulation run.
        $finish;
    end
endmodule

Lab02/alu_waveform.vcd
$date
	Tue May 26 22:45:55 2026
$end
$version
	Icarus Verilog
$end
$timescale
	1ps
$end
$scope module tb_alu $end
$var wire 8 ! RESULT [7:0] $end
$var reg 8 " DATA1 [7:0] $end
$var reg 8 # DATA2 [7:0] $end
$var reg 3 $ SELECT [2:0] $end
$scope module uut $end
$var wire 8 % DATA1 [7:0] $end
$var wire 8 & DATA2 [7:0] $end
$var wire 3 ' SELECT [2:0] $end
$var wire 8 ( or_out [7:0] $end
$var wire 8 ) fwd_out [7:0] $end
$var wire 8 * and_out [7:0] $end
$var wire 8 + add_out [7:0] $end
$var reg 8 , RESULT [7:0] $end
$scope module a1 $end
$var wire 8 - data1 [7:0] $end
$var wire 8 . data2 [7:0] $end
$var reg 8 / out [7:0] $end
$upscope $end
$scope module an1 $end
$var wire 8 0 data1 [7:0] $end
$var wire 8 1 data2 [7:0] $end
$var reg 8 2 out [7:0] $end
$upscope $end
$scope module f1 $end
$var wire 8 3 data2 [7:0] $end
$var reg 8 4 out [7:0] $end
$upscope $end
$scope module o1 $end
$var wire 8 5 data1 [7:0] $end
$var wire 8 6 data2 [7:0] $end
$var reg 8 7 out [7:0] $end
$upscope $end
$upscope $end
$upscope $end
$enddefinitions $end
$comment Show the parameter values. $end
$dumpall
$end
#0
$dumpvars
bx 7
b0 6
b0 5
bx 4
b0 3
bx 2
b0 1
b0 0
bx /
b0 .
b0 -
bx ,
bx +
bx *
bx )
bx (
b0 '
b0 &
b0 %
b0 $
b0 #
b0 "
bx !
$end
#1000
b0 !
b0 ,
b0 )
b0 4
b0 (
b0 7
b0 *
b0 2
#2000
b0 +
b0 /
#10000
b11001 #
b11001 &
b11001 .
b11001 1
b11001 3
b11001 6
b1010 "
b1010 %
b1010 -
b1010 0
b1010 5
#11000
b11001 !
b11001 ,
b11001 )
b11001 4
b1000 *
b1000 2
b11011 (
b11011 7
#12000
b100011 +
b100011 /
#20000
b100011 !
b100011 ,
b1 $
b1 '
#30000
b1000 !
b1000 ,
b10 $
b10 '
b10101010 #
b10101010 &
b10101010 .
b10101010 1
b10101010 3
b10101010 6
b11110000 "
b11110000 %
b11110000 -
b11110000 0
b11110000 5
#31000
b10100000 !
b10100000 ,
b10101010 )
b10101010 4
b11111010 (
b11111010 7
b10100000 *
b10100000 2
#32000
b10011010 +
b10011010 /
#40000
b11111010 !
b11111010 ,
b11 $
b11 '
b1111 #
b1111 &
b1111 .
b1111 1
b1111 3
b1111 6
#41000
b11111111 !
b11111111 ,
b0 *
b0 2
b11111111 (
b11111111 7
b1111 )
b1111 4
#42000
b11111111 +
b11111111 /
#50000
b0 !
b0 ,
b100 $
b100 '
b1100100 #
b1100100 &
b1100100 .
b1100100 1
b1100100 3
b1100100 6
b1100100 "
b1100100 %
b1100100 -
b1100100 0
b1100100 5
#51000
b1100100 )
b1100100 4
b1100100 (
b1100100 7
b1100100 *
b1100100 2
#52000
b11001000 +
b11001000 /
#55000
b111 $
b111 '
