Lab03/reg_file.v
// reg file for lab 2 part 2 (reusing for lab 3)
// 8x8 register file - 8 regs, 8 bits each
// 2 async read ports, 1 sync write port

module reg_file (IN, OUT1, OUT2, INADDRESS, OUT1ADDRESS, OUT2ADDRESS, WRITE, CLK, RESET);

    // data in port
    input [7:0] IN;

    // addresses (3 bits since we have 8 registers)
    input [2:0] INADDRESS;    // where to write to
    input [2:0] OUT1ADDRESS;  // read port 1
    input [2:0] OUT2ADDRESS;  // read port 2

    // control stuff
    input WRITE;   // write enable
    input CLK;     // clock
    input RESET;   // clears everything

    // outputs for reading
    output [7:0] OUT1;
    output [7:0] OUT2;

    // the actual registers array
    reg [7:0] registers [7:0];

    integer i; // for the loop below

    // read ports - async but with #2 delay as per lab manual
    assign #2 OUT1 = registers[OUT1ADDRESS];
    assign #2 OUT2 = registers[OUT2ADDRESS];

    // write and reset happen on posedge
    // reset has higher priority obviously
    always @(posedge CLK) begin

        if (RESET) begin
            // clear em all
            #1;
            for (i = 0; i < 8; i = i + 1) begin
                registers[i] <= 8'b00000000;
            end
        end

        else if (WRITE) begin
            // write input to the target register with #1 delay
            #1 registers[INADDRESS] <= IN;
        end

    end

endmodule

Lab03/alu.v
// 8-bit ALU for lab 3
// does mov, loadi, add, sub, and, or things

// gotta make a forward unit for mov and loadi instructions. 
// just passes data2 straight thru
// delay is #1
module forward_unit(input [7:0] data2, output reg [7:0] out);
    always @(*) #1 out = data2;
endmodule

// addition module. also used for sub (we do 2s complement in cpu module)
// this one takes 2 time units
module add_unit(input [7:0] data1, input [7:0] data2, output reg [7:0] out);
    always @(*) #2 out = data1 + data2;
endmodule

// bitwise AND. #1 delay
module and_unit(input [7:0] data1, input [7:0] data2, output reg [7:0] out);
    always @(*) #1 out = data1 & data2;
endmodule

// bitwise OR stuff. #1 delay
module or_unit(input [7:0] data1, input [7:0] data2, output reg [7:0] out);
    always @(*) #1 out = data1 | data2;
endmodule

// main alu module
// select codes:
// 000: forward
// 001: add
// 010: and
// 011: or
module alu (DATA1, DATA2, RESULT, SELECT); // 2 8-bit inputs
    input [7:0] DATA1, DATA2;
    input [2:0] SELECT;                    // 3 bit select signal
    output reg [7:0] RESULT;

    // wires for the module outputs
    wire [7:0] fwd_out, add_out, and_out, or_out;

    // run all of them at once bc why not
    forward_unit f1(DATA2, fwd_out);
    add_unit     a1(DATA1, DATA2, add_out);
    and_unit     an1(DATA1, DATA2, and_out);
    or_unit      o1(DATA1, DATA2, or_out);

    // mux to pick the right answer
    always @(*) begin
        case(SELECT)
            3'b000: RESULT = fwd_out;   // forward
            3'b001: RESULT = add_out;   // add
            3'b010: RESULT = and_out;   // and
            3'b011: RESULT = or_out;    // or
            default: RESULT = 8'b00000000; // just zero it out if something goes wrong
        endcase
    end
endmodule

Lab03/mux_2x1_8bit.v
module mux_2x1_8bit(
    input [7:0] IN0,
    input [7:0] IN1,
    input SEL,
    output reg [7:0] OUT
);

    // Assumption: MUX has negligible delay
    always @(*) begin
        case (SEL)
            1'b0: OUT = IN0;
            1'b1: OUT = IN1;
        endcase
    end

endmodule

Lab03/twos_complement.v
module twos_complement(
    input [7:0] IN,
    output reg [7:0] OUT
);

    // Computes the 2's complement (~value + 1)
    // Used for SUB instruction
    // Latency: #1 time unit
    always @(IN) begin
        #1 OUT = ~IN + 8'd1;
    end

endmodule

Lab03/control_unit.v
module control_unit(
    input [31:0] INSTRUCTION,
    output reg [2:0] READREG1,
    output reg [2:0] READREG2,
    output reg [2:0] WRITEREG,
    output reg WRITEENABLE,
    output reg [2:0] ALUOP,
    output reg MUX_IMM_SEL,
    output reg MUX_COMP_SEL,
    output reg [7:0] IMMEDIATE
);

    wire [7:0] OPCODE;
    wire [7:0] RD_IMM;
    wire [7:0] RT;
    wire [7:0] RS_IMM;

    assign OPCODE  = INSTRUCTION[31:24];
    assign RD_IMM  = INSTRUCTION[23:16];
    assign RT      = INSTRUCTION[15:8];
    assign RS_IMM  = INSTRUCTION[7:0];

    // Instruction Decode & Control Signal Generation
    // Decode delay: #1 time unit
    always @(INSTRUCTION) begin
        #1;  // Instruction decode delay
        
        // Default values for control signals
        WRITEENABLE = 1'b0;
        MUX_IMM_SEL = 1'b0;
        MUX_COMP_SEL = 1'b0;
        ALUOP = 3'b000;
        IMMEDIATE = RS_IMM;
        
        // Extract register addresses from instruction fields
        WRITEREG = RD_IMM[2:0];   // Destination register
        READREG1 = RT[2:0];        // Source register 1
        READREG2 = RS_IMM[2:0];    // Source register 2
        
        case (OPCODE)
            // LOADI
            8'b00000000: begin
                ALUOP = 3'b000;         // FORWARD operation
                MUX_IMM_SEL = 1'b1;     // Select immediate value
                MUX_COMP_SEL = 1'b0;    
                WRITEENABLE = 1'b1;      
                IMMEDIATE = RS_IMM;      
            end
            
            // MOV
            8'b00000001: begin
                ALUOP = 3'b000;         // FORWARD operation
                MUX_IMM_SEL = 1'b0;     
                MUX_COMP_SEL = 1'b0;    
                WRITEENABLE = 1'b1;      
                READREG2 = RT[2:0];      // Read the source register (RT)
            end
            
            // ADD
            8'b00000010: begin
                ALUOP = 3'b001;         // ADD operation
                MUX_IMM_SEL = 1'b0;     
                MUX_COMP_SEL = 1'b0;    
                WRITEENABLE = 1'b1;      
            end
            
            // SUB
            8'b00000011: begin
                ALUOP = 3'b001;         // ADD operation (add with 2's complement)
                MUX_IMM_SEL = 1'b0;     
                MUX_COMP_SEL = 1'b1;    // Select 2's complement of RS
                WRITEENABLE = 1'b1;      
            end
            
            // AND
            8'b00000100: begin
                ALUOP = 3'b010;         // AND operation
                MUX_IMM_SEL = 1'b0;     
                MUX_COMP_SEL = 1'b0;    
                WRITEENABLE = 1'b1;      
            end
            
            // OR
            8'b00000101: begin
                ALUOP = 3'b011;         // OR operation
                MUX_IMM_SEL = 1'b0;     
                MUX_COMP_SEL = 1'b0;    
                WRITEENABLE = 1'b1;      
            end
            
            default: begin
                WRITEENABLE = 1'b0;
            end
        endcase
    end

endmodule

Lab03/pc_unit.v
// program counter module
// just keeps track of where we are in the program
// increments by 4 each cycle (since each instruction is 4 bytes)

module pc_unit(
    output reg [31:0] PC,
    input CLK,
    input RESET
);

    wire [31:0] PC_NEXT;

    // calculate next PC value, #1 delay
    // this runs in parallel with the instruction memory read
    assign #1 PC_NEXT = PC + 32'd4;

    // update PC on clock edge
    always @(posedge CLK) begin
        if (RESET) begin
            #1 PC = 32'd0;         // go back to start
        end else begin
            #1 PC = PC_NEXT;       // move to next instruction
        end
    end

endmodule

Lab03/cpu.v
// Module: Top-Level CPU - Integration & Control
// Supports instructions: add, sub, and, or, mov, loadi
// This module integrates all components into a top-level datapath

module cpu(PC, INSTRUCTION, CLK, RESET);

    // Port Declarations
    output wire [31:0] PC;       // Program Counter (driven by pc_unit)
    input [31:0] INSTRUCTION;   // 32-bit instruction fetched from instruction memory
    input CLK;                  // Clock signal
    input RESET;                // Reset signal (synchronous)

    // Control Signals (generated by control_unit)
    wire [2:0] READREG1;        // Address for read port 1 of register file
    wire [2:0] READREG2;        // Address for read port 2 of register file
    wire [2:0] WRITEREG;        // Address for write port of register file
    wire WRITEENABLE;           // Write enable signal for register file
    wire [2:0] ALUOP;           // ALU operation select
    wire MUX_IMM_SEL;           // MUX select: 0 = register value, 1 = immediate value
    wire MUX_COMP_SEL;          // MUX select: 0 = original value, 1 = 2's complement
    wire [7:0] IMMEDIATE;       // Immediate value extracted from instruction

    // Internal Wires for Data Routing
    wire [7:0] REGOUT1;        // Output from register file port 1 (RT value)
    wire [7:0] REGOUT2;        // Output from register file port 2 (RS value)
    wire [7:0] ALURESULT;      // Result from ALU
    wire [7:0] TWOS_COMP_OUT;  // 2's complement of REGOUT2 (for SUB)
    wire [7:0] MUX_COMP_RESULT;// Output of 2's complement MUX
    wire [7:0] MUX_IMM_RESULT; // Output of immediate MUX

    // ============================================================
    // PC Unit Instantiation
    // ============================================================
    pc_unit mypc(
        .PC(PC),
        .CLK(CLK),
        .RESET(RESET)
    );

    // ============================================================
    // Control Unit Instantiation
    // ============================================================
    control_unit mycontrol(
        .INSTRUCTION(INSTRUCTION),
        .READREG1(READREG1),
        .READREG2(READREG2),
        .WRITEREG(WRITEREG),
        .WRITEENABLE(WRITEENABLE),
        .ALUOP(ALUOP),
        .MUX_IMM_SEL(MUX_IMM_SEL),
        .MUX_COMP_SEL(MUX_COMP_SEL),
        .IMMEDIATE(IMMEDIATE)
    );

    // ============================================================
    // 2's Complement Unit Instantiation
    // ============================================================
    twos_complement mytwoscomp(
        .IN(REGOUT2),
        .OUT(TWOS_COMP_OUT)
    );

    // ============================================================
    // MUX: 2's Complement Select
    // ============================================================
    mux_2x1_8bit mux_comp(
        .IN0(REGOUT2),
        .IN1(TWOS_COMP_OUT),
        .SEL(MUX_COMP_SEL),
        .OUT(MUX_COMP_RESULT)
    );

    // ============================================================
    // MUX: Immediate Value Select
    // ============================================================
    mux_2x1_8bit mux_imm(
        .IN0(MUX_COMP_RESULT),
        .IN1(IMMEDIATE),
        .SEL(MUX_IMM_SEL),
        .OUT(MUX_IMM_RESULT)
    );

    // ============================================================
    // ALU Instantiation
    // ============================================================
    alu myalu(
        .DATA1(REGOUT1),
        .DATA2(MUX_IMM_RESULT),
        .RESULT(ALURESULT),
        .SELECT(ALUOP)
    );

    // ============================================================
    // Register File Instantiation
    // ============================================================
    reg_file myreg(
        .IN(ALURESULT),
        .OUT1(REGOUT1),
        .OUT2(REGOUT2),
        .INADDRESS(WRITEREG),
        .OUT1ADDRESS(READREG1),
        .OUT2ADDRESS(READREG2),
        .WRITE(WRITEENABLE),
        .CLK(CLK),
        .RESET(RESET)
    );

endmodule

Lab03/cpu_tb.v
// testbench for the cpu
// tests all 6 instructions: loadi, mov, add, sub, and, or
// clock period = 8 time units

`include "cpu.v"
`include "alu.v"
`include "reg_file.v"
`include "control_unit.v"
`include "mux_2x1_8bit.v"
`include "pc_unit.v"
`include "twos_complement.v"

module cpu_tb;

    // testbench signals
    reg CLK, RESET;
    wire [31:0] PC;
    wire [31:0] INSTRUCTION;

    // instruction memory - 1024 bytes total
    // each instruction is 32 bits = 4 bytes
    reg [7:0] instr_mem [0:1023];

    // ============================================================
    // Instruction Fetching Logic (Asynchronous)
    // ============================================================
    // The CPU provides PC as the address; we read 4 bytes starting at PCYX
    // to form the 32-bit instruction word.
    // Instruction memory read delay: #2 time units
    assign #2 INSTRUCTION = {instr_mem[PC[31:0]+3], instr_mem[PC[31:0]+2], 
                              instr_mem[PC[31:0]+1], instr_mem[PC[31:0]]};

    // opcode reference:
    //   loadi = 00, mov = 01, add = 02, sub = 03, and = 04, or = 05
    // format: {opcode, rd, rt, rs/imm}

    initial begin
        // load the test program into memory

        // loadi r4, 5
        {instr_mem[10'd3], instr_mem[10'd2], instr_mem[10'd1], instr_mem[10'd0]}    = 32'b00000000_00000100_00000000_00000101;
        
        // loadi r2, 9
        {instr_mem[10'd7], instr_mem[10'd6], instr_mem[10'd5], instr_mem[10'd4]}    = 32'b00000000_00000010_00000000_00001001;
        
        // add r6, r4, r2  -> should be 14
        {instr_mem[10'd11], instr_mem[10'd10], instr_mem[10'd9], instr_mem[10'd8]}  = 32'b00000010_00000110_00000100_00000010;
        
        // mov r0, r6  -> r0 should be 14 now
        {instr_mem[10'd15], instr_mem[10'd14], instr_mem[10'd13], instr_mem[10'd12]} = 32'b00000001_00000000_00000110_00000000;
        
        // loadi r1, 1
        {instr_mem[10'd19], instr_mem[10'd18], instr_mem[10'd17], instr_mem[10'd16]} = 32'b00000000_00000001_00000000_00000001;
        
        // add r2, r2, r1  -> 9+1 = 10
        {instr_mem[10'd23], instr_mem[10'd22], instr_mem[10'd21], instr_mem[10'd20]} = 32'b00000010_00000010_00000010_00000001;
        
        // sub r3, r6, r4  -> 14-5 = 9
        {instr_mem[10'd27], instr_mem[10'd26], instr_mem[10'd25], instr_mem[10'd24]} = 32'b00000011_00000011_00000110_00000100;
        
        // and r5, r6, r2  -> 14 & 10 = 10
        {instr_mem[10'd31], instr_mem[10'd30], instr_mem[10'd29], instr_mem[10'd28]} = 32'b00000100_00000101_00000110_00000010;
        
        // or r7, r4, r1  -> 5 | 1 = 5
        {instr_mem[10'd35], instr_mem[10'd34], instr_mem[10'd33], instr_mem[10'd32]} = 32'b00000101_00000111_00000100_00000001;
        
        // loadi r3, 0xFF  (thats -1 in signed)
        {instr_mem[10'd39], instr_mem[10'd38], instr_mem[10'd37], instr_mem[10'd36]} = 32'b00000000_00000011_00000000_11111111;
        
        // add r5, r3, r4  -> -1 + 5 = 4
        {instr_mem[10'd43], instr_mem[10'd42], instr_mem[10'd41], instr_mem[10'd40]} = 32'b00000010_00000101_00000011_00000100;
        
        // sub r7, r4, r2  -> 5 - 10 = -5 (0xFB)
        {instr_mem[10'd47], instr_mem[10'd46], instr_mem[10'd45], instr_mem[10'd44]} = 32'b00000011_00000111_00000100_00000010;
        
        // loadi r0, 0xAA  (10101010 in binary)
        {instr_mem[10'd51], instr_mem[10'd50], instr_mem[10'd49], instr_mem[10'd48]} = 32'b00000000_00000000_00000000_10101010;
        
        // loadi r1, 0x55  (01010101)
        {instr_mem[10'd55], instr_mem[10'd54], instr_mem[10'd53], instr_mem[10'd52]} = 32'b00000000_00000001_00000000_01010101;
        
        // and r2, r0, r1  -> 0xAA & 0x55 = 0x00 (no overlapping bits)
        {instr_mem[10'd59], instr_mem[10'd58], instr_mem[10'd57], instr_mem[10'd56]} = 32'b00000100_00000010_00000000_00000001;
        
        // or r3, r0, r1  -> 0xAA | 0x55 = 0xFF (all bits set)
        {instr_mem[10'd63], instr_mem[10'd62], instr_mem[10'd61], instr_mem[10'd60]} = 32'b00000101_00000011_00000000_00000001;
        
        // mov r4, r3  -> r4 gets 0xFF
        {instr_mem[10'd67], instr_mem[10'd66], instr_mem[10'd65], instr_mem[10'd64]} = 32'b00000001_00000100_00000011_00000000;
    end

    // instantiate the cpu
    cpu mycpu(PC, INSTRUCTION, CLK, RESET);

    // simulation setup
    initial begin
        // dump waveforms for gtkwave
        $dumpfile("cpu_wavedata.vcd");
        $dumpvars(0, cpu_tb);
        $dumpvars(0, mycpu.myreg.registers[0]);
        $dumpvars(0, mycpu.myreg.registers[1]);
        $dumpvars(0, mycpu.myreg.registers[2]);
        $dumpvars(0, mycpu.myreg.registers[3]);
        $dumpvars(0, mycpu.myreg.registers[4]);
        $dumpvars(0, mycpu.myreg.registers[5]);
        $dumpvars(0, mycpu.myreg.registers[6]);
        $dumpvars(0, mycpu.myreg.registers[7]);
        
        // Initialize clock and reset
        CLK = 1'b0;
        RESET = 1'b0;
        
        // reset the cpu first
        #1 RESET = 1'b1;
        #10 RESET = 1'b0;
        
        // let it run for a while
        // 17 instructions * 8 time units each = ~136 but giving extra
        #500;
        
        // test reset mid-execution to make sure it actually works
        RESET = 1'b1;
        #10 RESET = 1'b0;
        
        // let it run a bit more after reset
        #200;
        
        $finish;
    end

    // clock gen - flip every 4 time units = period of 8
    always
        #4 CLK = ~CLK;

    // monitor for debugging - prints everything useful
    initial begin
        $monitor("Time=%0t | CLK=%b RESET=%b | PC=%0d | INSTRUCTION=%b | OPCODE=%b | RD=%0d RT=%0d RS=%0d | ALUOP=%b | WRITEENABLE=%b | ALURESULT=%0d",
                 $time, CLK, RESET, PC, INSTRUCTION, 
                 mycpu.mycontrol.OPCODE, mycpu.WRITEREG, mycpu.READREG1, mycpu.READREG2,
                 mycpu.ALUOP, mycpu.WRITEENABLE, mycpu.ALURESULT);
    end

endmodule

Lab03/cpu_wavedata.vcd
$date
	Tue Jun 09 09:59:02 2026
$end
$version
	Icarus Verilog
$end
$timescale
	1s
$end
$scope module cpu_tb $end
$var wire 32 ! PC [31:0] $end
$var wire 32 " INSTRUCTION [31:0] $end
$var reg 1 # CLK $end
$var reg 1 $ RESET $end
$scope module mycpu $end
$var wire 1 # CLK $end
$var wire 32 % INSTRUCTION [31:0] $end
$var wire 1 $ RESET $end
$var wire 3 & WRITEREG [2:0] $end
$var wire 1 ' WRITEENABLE $end
$var wire 8 ( TWOS_COMP_OUT [7:0] $end
$var wire 8 ) REGOUT2 [7:0] $end
$var wire 8 * REGOUT1 [7:0] $end
$var wire 3 + READREG2 [2:0] $end
$var wire 3 , READREG1 [2:0] $end
$var wire 32 - PC [31:0] $end
$var wire 1 . MUX_IMM_SEL $end
$var wire 8 / MUX_IMM_RESULT [7:0] $end
$var wire 1 0 MUX_COMP_SEL $end
$var wire 8 1 MUX_COMP_RESULT [7:0] $end
$var wire 8 2 IMMEDIATE [7:0] $end
$var wire 8 3 ALURESULT [7:0] $end
$var wire 3 4 ALUOP [2:0] $end
$scope module mux_comp $end
$var wire 1 0 SEL $end
$var wire 8 5 IN1 [7:0] $end
$var wire 8 6 IN0 [7:0] $end
$var reg 8 7 OUT [7:0] $end
$upscope $end
$scope module mux_imm $end
$var wire 8 8 IN0 [7:0] $end
$var wire 1 . SEL $end
$var wire 8 9 IN1 [7:0] $end
$var reg 8 : OUT [7:0] $end
$upscope $end
$scope module myalu $end
$var wire 8 ; DATA2 [7:0] $end
$var wire 8 < or_out [7:0] $end
$var wire 8 = fwd_out [7:0] $end
$var wire 8 > and_out [7:0] $end
$var wire 8 ? add_out [7:0] $end
$var wire 3 @ SELECT [2:0] $end
$var wire 8 A DATA1 [7:0] $end
$var reg 8 B RESULT [7:0] $end
$scope module a1 $end
$var wire 8 C data2 [7:0] $end
$var wire 8 D data1 [7:0] $end
$var reg 8 E out [7:0] $end
$upscope $end
$scope module an1 $end
$var wire 8 F data2 [7:0] $end
$var wire 8 G data1 [7:0] $end
$var reg 8 H out [7:0] $end
$upscope $end
$scope module f1 $end
$var wire 8 I data2 [7:0] $end
$var reg 8 J out [7:0] $end
$upscope $end
$scope module o1 $end
$var wire 8 K data2 [7:0] $end
$var wire 8 L data1 [7:0] $end
$var reg 8 M out [7:0] $end
$upscope $end
$upscope $end
$scope module mycontrol $end
$var wire 32 N INSTRUCTION [31:0] $end
$var wire 8 O RT [7:0] $end
$var wire 8 P RS_IMM [7:0] $end
$var wire 8 Q RD_IMM [7:0] $end
$var wire 8 R OPCODE [7:0] $end
$var reg 3 S ALUOP [2:0] $end
$var reg 8 T IMMEDIATE [7:0] $end
$var reg 1 0 MUX_COMP_SEL $end
$var reg 1 . MUX_IMM_SEL $end
$var reg 3 U READREG1 [2:0] $end
$var reg 3 V READREG2 [2:0] $end
$var reg 1 ' WRITEENABLE $end
$var reg 3 W WRITEREG [2:0] $end
$upscope $end
$scope module mypc $end
$var wire 1 # CLK $end
$var wire 1 $ RESET $end
$var wire 32 X PC_NEXT [31:0] $end
$var reg 32 Y PC [31:0] $end
$upscope $end
$scope module myreg $end
$var wire 1 # CLK $end
$var wire 8 Z IN [7:0] $end
$var wire 3 [ INADDRESS [2:0] $end
$var wire 8 \ OUT1 [7:0] $end
$var wire 3 ] OUT1ADDRESS [2:0] $end
$var wire 8 ^ OUT2 [7:0] $end
$var wire 3 _ OUT2ADDRESS [2:0] $end
$var wire 1 $ RESET $end
$var wire 1 ' WRITE $end
$var integer 32 ` i [31:0] $end
$upscope $end
$scope module mytwoscomp $end
$var wire 8 a IN [7:0] $end
$var reg 8 b OUT [7:0] $end
$upscope $end
$upscope $end
$upscope $end
$scope module cpu_tb $end
$scope module mycpu $end
$scope module myreg $end
$var reg 8 c \registers[0] [7:0] $end
$upscope $end
$upscope $end
$upscope $end
$scope module cpu_tb $end
$scope module mycpu $end
$scope module myreg $end
$var reg 8 d \registers[1] [7:0] $end
$upscope $end
$upscope $end
$upscope $end
$scope module cpu_tb $end
$scope module mycpu $end
$scope module myreg $end
$var reg 8 e \registers[2] [7:0] $end
$upscope $end
$upscope $end
$upscope $end
$scope module cpu_tb $end
$scope module mycpu $end
$scope module myreg $end
$var reg 8 f \registers[3] [7:0] $end
$upscope $end
$upscope $end
$upscope $end
$scope module cpu_tb $end
$scope module mycpu $end
$scope module myreg $end
$var reg 8 g \registers[4] [7:0] $end
$upscope $end
$upscope $end
$upscope $end
$scope module cpu_tb $end
$scope module mycpu $end
$scope module myreg $end
$var reg 8 h \registers[5] [7:0] $end
$upscope $end
$upscope $end
$upscope $end
$scope module cpu_tb $end
$scope module mycpu $end
$scope module myreg $end
$var reg 8 i \registers[6] [7:0] $end
$upscope $end
$upscope $end
$upscope $end
$scope module cpu_tb $end
$scope module mycpu $end
$scope module myreg $end
$var reg 8 j \registers[7] [7:0] $end
$upscope $end
$upscope $end
$upscope $end
$scope module cpu_tb $end
$scope module mycpu $end
$scope module myreg $end
$var reg 8 T \registers[0] [7:0] $end
$upscope $end
$upscope $end
$upscope $end
$scope module cpu_tb $end
$scope module mycpu $end
$scope module myreg $end
$var reg 8 U \registers[1] [7:0] $end
$upscope $end
$upscope $end
$upscope $end
$scope module cpu_tb $end
$scope module mycpu $end
$scope module myreg $end
$var reg 8 V \registers[2] [7:0] $end
$upscope $end
$upscope $end
$upscope $end
$scope module cpu_tb $end
$scope module mycpu $end
$scope module myreg $end
$var reg 8 W \registers[3] [7:0] $end
$upscope $end
$upscope $end
$upscope $end
$scope module cpu_tb $end
$scope module mycpu $end
$scope module myreg $end
$var reg 8 X \registers[4] [7:0] $end
$upscope $end
$upscope $end
$upscope $end
$scope module cpu_tb $end
$scope module mycpu $end
$scope module myreg $end
$var reg 8 Y \registers[5] [7:0] $end
$upscope $end
$upscope $end
$upscope $end
$scope module cpu_tb $end
$scope module mycpu $end
$scope module myreg $end
$var reg 8 Z \registers[6] [7:0] $end
$upscope $end
$upscope $end
$upscope $end
$scope module cpu_tb $end
$scope module mycpu $end
$scope module myreg $end
$var reg 8 [ \registers[7] [7:0] $end
$upscope $end
$upscope $end
$upscope $end
$enddefinitions $end
$comment Show the parameter values. $end
$dumpall
$end
#0
$dumpvars
bx [
bx Z
bx Y
bx X
bx W
bx V
bx U
bx T
bx S
bx R
bx Q
bx P
bx O
bx N
bx M
bx L
bx K
bx J
bx I
bx H
bx G
bx F
bx E
bx D
bx C
bx B
bx A
bx @
bx ?
bx >
bx =
bx <
bx ;
bx :
bx 9
bx 8
bx 7
bx 6
bx 5
bx 4
bx 3
bx 2
bx 1
x0
bx /
x.
bx -
bx ,
bx +
bx *
bx )
bx (
x'
bx &
bx %
0$
0#
bx "
bx !
$end
#1
1$
#4
1#
#5
b0 [
b0 Z
b0 Y
b0 X
b0 W
b0 V
b0 U
b0 T
b1000 S
b0 !
b0 -
b0 Y
b1000 `
#6
b100 X
#7
b0 R
b100 Q
b0 O
b101 P
b1000000000000000101 "
b1000000000000000101 %
b1000000000000000101 N
#8
b101 /
b101 :
b101 ;
b101 C
b101 F
b101 I
b101 K
b101 +
b101 V
b101 _
b0 ,
b0 U
b0 ]
b100 &
b100 W
b100 [
b101 2
b101 9
b101 T
b0 4
b0 @
b0 S
00
1.
1'
0#
#9
b101 3
b101 B
b101 Z
bx1x1 <
bx1x1 M
b0x0x >
b0x0x H
b101 =
b101 J
#10
b0 1
b0 7
b0 8
b101 ?
b101 E
b0 )
b0 6
b0 ^
b0 a
b0 *
b0 A
b0 D
b0 G
b0 L
b0 \
#11
b0 (
b0 5
b0 b
b0 >
b0 H
b101 <
b101 M
0$
#12
1#
#13
b101 X
b100 !
b100 -
b100 Y
#14
b1000 X
#15
b10 Q
b1001 P
b100000000000001001 "
b100000000000001001 %
b100000000000001001 N
#16
b1001 /
b1001 :
b1001 ;
b1001 C
b1001 F
b1001 I
b1001 K
b1 +
b1 V
b1 _
b10 &
b10 W
b10 [
b1001 2
b1001 9
b1001 T
1.
1'
0#
#17
b1001 3
b1001 B
b1001 Z
b1001 <
b1001 M
b1001 =
b1001 J
#18
b1001 ?
b1001 E
#20
1#
#21
b1001 V
b1000 !
b1000 -
b1000 Y
#22
b1100 X
#23
b10 R
b110 Q
b100 O
b10 P
b10000001100000010000000010 "
b10000001100000010000000010 %
b10000001100000010000000010 N
#24
b0 /
b0 :
b0 ;
b0 C
b0 F
b0 I
b0 K
b1 4
b1 @
b1 S
b10 +
b10 V
b10 _
b100 ,
b100 U
b100 ]
b110 &
b110 W
b110 [
b10 2
b10 9
b10 T
0.
1'
0#
#25
b0 <
b0 M
b0 =
b0 J
#26
b1001 /
b1001 :
b1001 ;
b1001 C
b1001 F
b1001 I
b1001 K
b101 3
b101 B
b101 Z
b1001 1
b1001 7
b1001 8
b101 ?
b101 E
b1001 )
b1001 6
b1001 ^
b1001 a
b101 *
b101 A
b101 D
b101 G
b101 L
b101 \
#27
b1001 =
b1001 J
b11110111 (
b11110111 5
b11110111 b
b1101 <
b1101 M
b1 >
b1 H
#28
b1110 3
b1110 B
b1110 Z
b1110 ?
b1110 E
1#
#29
b1110 Z
b1100 !
b1100 -
b1100 Y
#30
b10000 X
#31
b1 R
b0 Q
b110 O
b0 P
b1000000000000011000000000 "
b1000000000000011000000000 %
b1000000000000011000000000 N
#32
b1001 3
b1001 B
b1001 Z
b110 +
b110 V
b110 _
b110 ,
b110 U
b110 ]
b0 &
b0 W
b0 [
b0 2
b0 9
b0 T
b0 4
b0 @
b0 S
1'
0#
#34
b1110 /
b1110 :
b1110 ;
b1110 C
b1110 F
b1110 I
b1110 K
b1110 1
b1110 7
b1110 8
b1110 )
b1110 6
b1110 ^
b1110 a
b1110 *
b1110 A
b1110 D
b1110 G
b1110 L
b1110 \
#35
b1110 3
b1110 B
b1110 Z
b1110 =
b1110 J
b11110010 (
b11110010 5
b11110010 b
b1110 >
b1110 H
b1110 <
b1110 M
#36
b11100 ?
b11100 E
1#
#37
b1110 T
b10000 !
b10000 -
b10000 Y
#38
b10100 X
#39
b0 R
b1 Q
b0 O
b1 P
b10000000000000001 "
b10000000000000001 %
b10000000000000001 N
#40
b1 /
b1 :
b1 ;
b1 C
b1 F
b1 I
b1 K
1.
b1 +
b1 V
b1 _
b0 ,
b0 U
b0 ]
b1 &
b1 W
b1 [
b1 2
b1 9
b1 T
1'
0#
#41
b1 3
b1 B
b1 Z
b1111 <
b1111 M
b0 >
b0 H
b1 =
b1 J
#42
b0 1
b0 7
b0 8
b1111 ?
b1111 E
b0 )
b0 6
b0 ^
b0 a
#43
b0 (
b0 5
b0 b
#44
1#
#45
b1 U
b10100 !
b10100 -
b10100 Y
#46
b11000 X
#47
b1 1
b1 7
b1 8
b10 R
b10 Q
b10 O
b1 )
b1 6
b1 ^
b1 a
b10000000100000001000000001 "
b10000000100000001000000001 %
b10000000100000001000000001 N
#48
b1111 3
b1111 B
b1111 Z
b11111111 (
b11111111 5
b11111111 b
b1 4
b1 @
b1 S
b10 ,
b10 U
b10 ]
b10 &
b10 W
b10 [
0.
1'
0#
#50
b1001 *
b1001 A
b1001 D
b1001 G
b1001 L
b1001 \
#51
b1 >
b1 H
b1001 <
b1001 M
#52
b1010 3
b1010 B
b1010 Z
b1010 ?
b1010 E
1#
#53
b1010 V
b11000 !
b11000 -
b11000 Y
#54
b11100 X
#55
b11 R
b11 Q
b110 O
b100 P
b1010 *
b1010 A
b1010 D
b1010 G
b1010 L
b1010 \
b11000000110000011000000100 "
b11000000110000011000000100 %
b11000000110000011000000100 N
#56
b11111111 /
b11111111 :
b11111111 ;
b11111111 C
b11111111 F
b11111111 I
b11111111 K
b11111111 1
b11111111 7
b11111111 8
b1011 <
b1011 M
b0 >
b0 H
10
b100 +
b100 V
b100 _
b110 ,
b110 U
b110 ]
b11 &
b11 W
b11 [
b100 2
b100 9
b100 T
b1 4
b1 @
b1 S
1'
0#
#57
b1001 3
b1001 B
b1001 Z
b1010 >
b1010 H
b11111111 <
b11111111 M
b11111111 =
b11111111 J
b1001 ?
b1001 E
#58
b101 )
b101 6
b101 ^
b101 a
b1110 *
b1110 A
b1110 D
b1110 G
b1110 L
b1110 \
#59
b11111011 /
b11111011 :
b11111011 ;
b11111011 C
b11111011 F
b11111011 I
b11111011 K
b11111011 1
b11111011 7
b11111011 8
b11111011 (
b11111011 5
b11111011 b
b1110 >
b1110 H
#60
b1010 >
b1010 H
b11111011 =
b11111011 J
1#
#61
b1001 W
b11100 !
b11100 -
b11100 Y
#62
b100000 X
#63
b100 R
b101 Q
b10 P
b100000001010000011000000010 "
b100000001010000011000000010 %
b100000001010000011000000010 N
#64
b101 /
b101 :
b101 ;
b101 C
b101 F
b101 I
b101 K
b1010 3
b1010 B
b1010 Z
b101 1
b101 7
b101 8
b10 +
b10 V
b10 _
b101 &
b101 W
b101 [
b10 2
b10 9
b10 T
b10 4
b10 @
b10 S
00
1'
0#
#65
b100 3
b100 B
b100 Z
b1111 <
b1111 M
b100 >
b100 H
b101 =
b101 J
#66
b1010 /
b1010 :
b1010 ;
b1010 C
b1010 F
b1010 I
b1010 K
b1010 1
b1010 7
b1010 8
b10011 ?
b10011 E
b1010 )
b1010 6
b1010 ^
b1010 a
#67
b1010 3
b1010 B
b1010 Z
b1010 >
b1010 H
b1110 <
b1110 M
b1010 =
b1010 J
b11110110 (
b11110110 5
b11110110 b
#68
b11000 ?
b11000 E
1#
#69
b1010 Y
b100000 !
b100000 -
b100000 Y
#70
b100100 X
#71
b101 R
b111 Q
b100 O
b1 P
b101000001110000010000000001 "
b101000001110000010000000001 %
b101000001110000010000000001 N
#72
b1110 3
b1110 B
b1110 Z
b1 +
b1 V
b1 _
b100 ,
b100 U
b100 ]
b111 &
b111 W
b111 [
b1 2
b1 9
b1 T
b11 4
b11 @
b11 S
1'
0#
#74
b1 /
b1 :
b1 ;
b1 C
b1 F
b1 I
b1 K
b1 1
b1 7
b1 8
b1 )
b1 6
b1 ^
b1 a
b101 *
b101 A
b101 D
b101 G
b101 L
b101 \
#75
b101 3
b101 B
b101 Z
b1 =
b1 J
b11111111 (
b11111111 5
b11111111 b
b101 <
b101 M
b1 >
b1 H
