Lab02/Task2/reg_file.v
module reg_file (IN, OUT1, OUT2, INADDRESS, OUT1ADDRESS, OUT2ADDRESS, WRITE, CLK, RESET);

    //Input Ports

    // 8 bit data input that we write into a register
    input [7:0] IN;

    //3 bit addresses to select which register to access
    input [2:0] INADDRESS; //register we write to
    input [2:0] OUT1ADDRESS; // register to read from for port 1
    input [2:0] OUT2ADDRESS; //register to read from for port 2

    //control signals
    input WRITE; // enables writing
    input CLK;
    input RESET; // clears all registers when high

    //Output ports
    // two 8 bit outputs to read two registers at the same time
    output [7:0] OUT1;
    output [7:0] OUT2;

    // the register file itself
    //8 registers each 8 bits wide
    reg [7:0] registers [7:0];

    integer i; // for the reset loop

    // Asynchronous reading
    // outputs update whenever address changes, no need to wait for clock
    // #2 is the read delay
    assign #2 OUT1 = registers[OUT1ADDRESS];
    assign #2 OUT2 = registers[OUT2ADDRESS];

    //synchronous write and reset
    // runs on rising edge of clock only
    // reset takes priority over write
    always @(posedge CLK) begin

        if (RESET) begin
            // clear all registers to zero
            #1;
            for (i = 0; i < 8; i = i + 1) begin
                registers[i] <= 8'b00000000;
            end
        end

        else if (WRITE) begin
            // write IN to the register at INADDRESS
            #1 registers[INADDRESS] <= IN;
        end

    end

endmodule

Lab02/reg_file_tb/reg_file_tb.v
// Computer Architecture CO2070 - Lab 02
// Design: Register File of Simple Processor
// Author: Kisaru Liyanage

module reg_file_tb;
    
    reg [7:0] WRITEDATA;
    reg [2:0] WRITEREG, READREG1, READREG2;
    reg CLK, RESET, WRITEENABLE; 
    wire [7:0] REGOUT1, REGOUT2;
    
    reg_file myregfile(WRITEDATA, REGOUT1, REGOUT2, WRITEREG, READREG1, READREG2, WRITEENABLE, CLK, RESET);
       
    initial
    begin
        CLK = 1'b1;
        
        // generate files needed to plot the waveform using GTKWave
        $dumpfile("reg_file_wavedata.vcd");
		$dumpvars(0, reg_file_tb);
        
        // assign values with time to input signals to see output 
        RESET = 1'b0;
        WRITEENABLE = 1'b0;
        
        #4
        RESET = 1'b1;
        READREG1 = 3'd0;
        READREG2 = 3'd4;
        
        #6
        RESET = 1'b0;
        
        #2
        WRITEREG = 3'd2;
        WRITEDATA = 8'd95;
        WRITEENABLE = 1'b1;
        
        #7
        WRITEENABLE = 1'b0;
        
        #1
        READREG1 = 3'd2;
        
        #7
        WRITEREG = 3'd1;
        WRITEDATA = 8'd28;
        WRITEENABLE = 1'b1;
        READREG1 = 3'd1;
        
        #8
        WRITEENABLE = 1'b0;
        
        #8
        WRITEREG = 3'd4;
        WRITEDATA = 8'd6;
        WRITEENABLE = 1'b1;
        
        #8
        WRITEDATA = 8'd15;
        WRITEENABLE = 1'b1;
        
        #10
        WRITEENABLE = 1'b0;
        
        #6
        WRITEREG = -3'd1;
        WRITEDATA = 8'd50;
        WRITEENABLE = 1'b1;
        
        #5
        WRITEENABLE = 1'b0;
        
        #10
        $finish;
    end
    
    // clock signal generation
    always
        #4 CLK = ~CLK;
        

endmodule

Lab02/reg_file_tb/reg_file_wavedata.vcd
$date
	Tue Jan 11 11:11:56 2022
$end
$version
	Icarus Verilog
$end
$timescale
	1s
$end
$scope module reg_file_tb $end
$var wire 8 ! REGOUT2 [7:0] $end
$var wire 8 " REGOUT1 [7:0] $end
$var reg 1 # CLK $end
$var reg 3 $ READREG1 [2:0] $end
$var reg 3 % READREG2 [2:0] $end
$var reg 1 & RESET $end
$var reg 8 ' WRITEDATA [7:0] $end
$var reg 1 ( WRITEENABLE $end
$var reg 3 ) WRITEREG [2:0] $end
$scope module myregfile $end
$var wire 1 # CLK $end
$var wire 8 * IN [7:0] $end
$var wire 3 + INADDRESS [2:0] $end
$var wire 8 , OUT1 [7:0] $end
$var wire 3 - OUT1ADDRESS [2:0] $end
$var wire 8 . OUT2 [7:0] $end
$var wire 3 / OUT2ADDRESS [2:0] $end
$var wire 1 & RESET $end
$var wire 1 ( WRITE $end
$var integer 32 0 i [31:0] $end
$upscope $end
$upscope $end
$enddefinitions $end
#0
$dumpvars
bx 0
bx /
bx .
bx -
bx ,
bx +
bx *
bx )
0(
bx '
0&
bx %
bx $
1#
bx "
bx !
$end
#4
0#
b100 %
b100 /
b0 $
b0 -
1&
#8
1#
#9
b1000 0
#10
0&
#11
b0 !
b0 .
b0 "
b0 ,
#12
1(
b1011111 '
b1011111 *
b10 )
b10 +
0#
#16
1#
#19
0(
#20
b10 $
b10 -
0#
#22
b1011111 "
b1011111 ,
#24
1#
#27
b1 $
b1 -
1(
b11100 '
b11100 *
b1 )
b1 +
#28
0#
#29
b0 "
b0 ,
#32
1#
#35
b11100 "
b11100 ,
0(
#36
0#
#40
1#
#43
1(
b110 '
b110 *
b100 )
b100 +
#44
0#
#48
1#
#51
b110 !
b110 .
b1111 '
b1111 *
#52
0#
#56
1#
#59
b1111 !
b1111 .
#60
0#
#61
0(
#64
1#
#67
1(
b110010 '
b110010 *
b111 )
b111 +
#68
0#
#72
1#
0(
